arb/__init__.py
arb/bot-fake-money.py
arb/bot.py
arb/delta_neutral_config.py
arb/exchange_config.py
arb/latency.py
arb/main.py
arb/run.py
arb-0.1.2.dist-info/METADATA
arb-0.1.2.dist-info/WHEEL
arb-0.1.2.dist-info/entry_points.txt
arb-0.1.2.dist-info/top_level.txt
arb-0.1.2.dist-info/RECORD
