Metadata-Version: 2.1
Name: arb
Version: 0.1.2
Requires-Dist: ccxt
Requires-Dist: colorama==0.4.6
Requires-Dist: requests==2.31.0
Requires-Dist: pytz==2023.3
